MANIFEST.in
README.md
setup.cfg
setup.py
version.txt
bin/prude
prude/__init__.py
prude/arg.py
prude/debug.py
prude/english.py
prude/env.py
prude/module.py
prude/tools.py
prude.egg-info/PKG-INFO
prude.egg-info/SOURCES.txt
prude.egg-info/dependency_links.txt
prude.egg-info/not-zip-safe
prude.egg-info/top_level.txt