Metadata-Version: 2.1
Name: prude
Version: 0.3.2
Summary: Prude is a simple parser that check word error (CamelCase variable, snake_case variable and Documentation)
Home-page: http://github.com/HeeroYui/prude
Author: Edouard DUPIN
Author-email: yui.heero@gmail.com
License: APACHE-2
Keywords: language checker in code
Platform: UNKNOWN
Classifier: Development Status :: 4 - Beta
Classifier: License :: OSI Approved :: Apache Software License
Classifier: Programming Language :: Python
Classifier: Topic :: Software Development :: Build Tools
Classifier: Topic :: Software Development :: Documentation
Classifier: Topic :: Software Development :: Testing
